Metadata-Version: 1.1
Name: mdtemplater
Version: 0.1
Summary: Creates a markdown file for note taking
Home-page: https://github.com/CoolDudde4150/mdtemplater
Author: CoolDudde4150
Author-email: UNKNOWN
License: MIT
Download-URL: https://github.com/CoolDudde4150/mdtemplater/archive/v0.1.tar.gz
Platform: UNKNOWN
